machine_tracking/__init__.py
machine_tracking/filtersets.py
machine_tracking/forms.py
machine_tracking/models.py
machine_tracking/navigation.py
machine_tracking/tables.py
machine_tracking/template_content.py
machine_tracking/urls.py
machine_tracking/views.py
machine_tracking/api/__init__.py
machine_tracking/api/serializers.py
machine_tracking/api/urls.py
machine_tracking/api/views.py
machine_tracking/migrations/0001_initial.py
machine_tracking/migrations/0002_event_part_type.py
machine_tracking/migrations/0003_alter_replacement_part_type.py
machine_tracking/migrations/__init__.py
machine_tracking/templates/machine_tracking/device_panel.html
machine_tracking/templates/machine_tracking/event.html
machine_tracking/templates/machine_tracking/replacement.html
netbox_plugin_machine_tracking-0.0.5.dist-info/METADATA
netbox_plugin_machine_tracking-0.0.5.dist-info/WHEEL
netbox_plugin_machine_tracking-0.0.5.dist-info/licenses/LICENCE
netbox_plugin_machine_tracking-0.0.5.dist-info/RECORD
