Metadata-Version: 2.1
Name: netbox-plugin-machine-tracking
Version: 0.0.5
Summary: A Netbox plugin tracking failures and other state changes in devices.
Author-email: Lisa Guo <lisguo@cisco.com>
License-File: LICENCE
Classifier: License :: OSI Approved :: MIT License
Classifier: Operating System :: OS Independent
Classifier: Programming Language :: Python :: 3
Requires-Python: >=3.7
